<?xml version="1.0" encoding="windows-1251" standalone="no"?>
<KFile Name="K_B_00026016_000785_101122.XML" Version="1.0" Schema="2.0" Hash="A7" CRC="754B832067787483"><Head NumTerm="26016" SmenaNum="785" PlaceTerm="2004182" Month="34" TimeOpen="22.11.2010 11:40:00" FirstTicket="515" TypeTerm="ÌÊÒÊ" SoftVersion="ÑÁÐ.001.059.002TK/26.11.2009WN" INN="007839330845" FIO="ÎÑÈÏÎÂÀ=ËÏ" Sum="30" Sup="0" SumEKLZ="30" TimeClose="22.11.2010 11:42:00" NumTickets="3" LenTape="2.29" CardIn="0" CardOut="0" Cancel="30" SumProc="0" NumProc="0"/><History N="5"><Event N="1" T="24.11.2010 7:05:00" C="1" O="CREATE(TCP_CONC 1.72) xx_dll.dll v.1.0.0.29" E="0"/><Event N="2" T="24.11.2010 7:39:28" C="2" O="SPPD ARM2.exe v.1.3.0.26 tarif:t_001_04003_00038_100831.xml" E="0"/><Event N="3" T="01.12.2010 9:59:25" C="2" O="SPPD ARM2.exe v.1.3.0.26 tarif:t_001_04003_00038_100831.xml" E="0"/><Event N="4" T="01.12.2010 10:11:24" C="4" O="MTS+ Marsh75.exe ver. 10.6.9.100" E="0"/><Event N="5" T="01.12.2010 10:36:45" C="2" O="SPPD ARM2.exe v.1.3.0.28 tarif:t_001_04003_00038_100831.xml" E="0"/></History><ServOp><Test N="515" T="22.11.2010 11:40:00"/><Cancel N="517" T="22.11.2010 11:41:00" S="30" Z="516"/><Rep N="0" T="22.11.2010 11:42:00"/></ServOp><ZalogOp/><ServForms/><Perevoz Gkey="0600"><TrainCat Cat="Î"><TPlan ID="0"><FromStation E="2004182"><ToStation E="2004181" D="3"><TicketType ID="1"><Ticket N="516" T="22.11.2010 11:41:00" S="30" A="1"/></TicketType></ToStation></FromStation></TPlan></TrainCat></Perevoz></KFile>
