<?xml version="1.0" encoding="windows-1251" standalone="no"?>
<KFile Name="K_B_00024362_000325_101031.XML" Version="1.0" Schema="2.0" Hash="88" CRC="51139CBA84961F76"><Head NumTerm="24362" SmenaNum="325" PlaceTerm="2004180" Month="19" TimeOpen="31.10.2010 19:22:00" FirstTicket="1" TypeTerm="ÌÊÒÊ" SoftVersion="ÑÁÐ.001.059.002TK/26.11.2009WN" INN="007839330845" FIO="ÊÀÏÐÀËÎÂÀ=ÌÑ" Sum="16369.8" Sup="3438.7" SumEKLZ="16369.8" TimeClose="01.11.2010 7:06:00" NumTickets="121" LenTape="14.63" CardIn="0" CardOut="0" Cancel="0" SumProc="16369.8" NumProc="120"/><History N="4"><Event N="1" T="09.11.2010 9:33:00" C="1" O="CREATE(PED_Reader v.1.1.0.13) xx_dll.dll v.1.0.0.29" E="0"/><Event N="2" T="11.11.2010 10:20:41" C="2" O="SPPD ARM2.exe v.1.3.0.26 tarif:t_001_04003_00038_100831.xml" E="0"/><Event N="3" T="11.11.2010 10:35:13" C="4" O="MTS+ Marsh75.exe ver. 10.6.9.100" E="0"/><Event N="4" T="11.11.2010 11:24:05" C="2" O="SPPD ARM2.exe v.1.3.0.28 tarif:t_001_04003_00038_100831.xml" E="0"/></History><ServOp><Test N="1" T="31.10.2010 19:22:00"/><Rep N="0" T="01.11.2010 7:06:00"/></ServOp><ZalogOp/><ServForms/><Perevoz Gkey="0600"><TrainCat Cat="Î"><TPlan ID="0"><FromStation E="2004180"><ToStation E="2005020" D="51"><TicketType ID="1"><Ticket N="2" T="31.10.2010 19:33:00" S="76.5"/><Ticket N="3" T="31.10.2010 19:35:00" S="76.5"/><Ticket N="12" T="31.10.2010 20:07:00" S="76.5"/><Ticket N="13" T="31.10.2010 20:07:00" S="76.5"/><Ticket N="20" T="31.10.2010 20:59:00" S="76.5"/></TicketType><TicketType ID="1" L="2422"><Ticket N="37" T="01.11.2010 5:28:00" S="0" U="153" R="1" V="4" D="07762033772" F="ÑÀÌÑÎÍÎÂÀ=ÃÀ"/></TicketType><TicketType ID="1" L="2416"><Ticket N="62" T="01.11.2010 6:00:00" S="0" U="153" R="1" V="4" D="06729478510" F="ÄÎÁÐÎÂÎËÜÑÊÈÉ=ÀÃ"/></TicketType></ToStation><ToStation E="2005096" D="20"><TicketType ID="1"><Ticket N="4" T="31.10.2010 19:36:00" S="30"/></TicketType></ToStation><ToStation E="2004003" D="59"><TicketType ID="1"><Ticket N="5" T="31.10.2010 19:37:00" S="88.5"/><Ticket N="22" T="31.10.2010 21:32:00" S="88.5"/><Ticket N="30" T="01.11.2010 4:42:00" S="88.5"/><Ticket N="32" T="01.11.2010 4:44:00" S="88.5"/><Ticket N="36" T="01.11.2010 5:22:00" S="177" R="1"/><Ticket N="40" T="01.11.2010 5:38:00" S="177" R="1"/><Ticket N="42" T="01.11.2010 5:40:00" S="177" R="1"/><Ticket N="43" T="01.11.2010 5:41:00" S="177" R="1"/><Ticket N="53" T="01.11.2010 5:56:00" S="177" R="1"/><Ticket N="72" T="01.11.2010 6:22:00" S="177" R="1"/><Ticket N="90" T="01.11.2010 6:37:00" S="177" R="1"/><Ticket N="92" T="01.11.2010 6:37:00" S="88.5"/><Ticket N="93" T="01.11.2010 6:37:00" S="177" R="1"/><Ticket N="98" T="01.11.2010 6:39:00" S="177" R="1"/><Ticket N="100" T="01.11.2010 6:40:00" S="88.5"/><Ticket N="104" T="01.11.2010 6:41:00" S="177" R="1"/><Ticket N="107" T="01.11.2010 6:44:00" S="177" R="1"/><Ticket N="110" T="01.11.2010 6:51:00" S="177" R="1"/><Ticket N="112" T="01.11.2010 6:52:00" S="88.5"/><Ticket N="118" T="01.11.2010 6:57:00" S="88.5"/></TicketType><TicketType ID="1" L="2422"><Ticket N="6" T="31.10.2010 19:38:00" S="0" U="88.5" V="4" D="11385195960" F="ÃÀËÜÖÅÂ=ÑÃ"/><Ticket N="7" T="31.10.2010 19:39:00" S="0" U="88.5" V="4" D="01626201405" F="ÏÅÒÐÎÂ=ÂÍ"/><Ticket N="34" T="01.11.2010 4:55:00" S="0" U="177" R="1" V="4" D="08201292223" F="ÏÅÒÐÀÊÎÂÀ=ÍÍ"/><Ticket N="35" T="01.11.2010 4:55:00" S="0" U="177" R="1" V="4" D="00774838875" F="ÌÈÕÀÉËÎÂÀ=ÇÍ"/><Ticket N="39" T="01.11.2010 5:38:00" S="0" U="177" R="1" V="4" D="00703402690" F="ÔÅÄÎÑÅÍÊÎ=ÍÈ"/><Ticket N="77" T="01.11.2010 6:30:00" S="0" U="177" R="1" V="4" D="02660992060" F="ÁÎÃÎÌÎËÎÂ=ÍÂ"/><Ticket N="85" T="01.11.2010 6:35:00" S="0" U="177" R="1" V="4" D="00377374341" F="ÂÎËÊÎÂÀ=ÒÍ"/></TicketType><TicketType ID="405"><Ticket N="9" T="31.10.2010 20:02:00" S="1529" P="01.11.2010" C="00000000000001694272" K="98363847"/></TicketType><TicketType ID="1" L="2416"><Ticket N="31" T="01.11.2010 4:43:00" S="0" U="177" R="1" V="4" D="02145422199" F="ßÑÎÂÅÅÂ=ÐÕ"/><Ticket N="45" T="01.11.2010 5:43:00" S="0" U="177" R="1" V="4" D="00376974158" F="ÁÓÐß×ÊÎÂÀ=ÇÃ"/></TicketType><TicketType ID="1" L="2203"><Ticket N="55" T="01.11.2010 5:58:00" S="0" U="177" R="1" C="00000020080045663494" K="342297118" V="7" H="Ð" B="01137" O="7000009806" F="ÒÀÍÀÍÎÂ=ÑÅÐÃÅÉ=ÂÀÑÈËÜÅÂÈ×" SN="00301059968"/></TicketType><TicketType ID="1" L="2605"><Ticket N="66" T="01.11.2010 6:04:00" S="88.5" U="88.5" R="1"/><Ticket N="111" T="01.11.2010 6:51:00" S="88.5" U="88.5" R="1"/><Ticket N="113" T="01.11.2010 6:53:00" S="88.5" U="88.5" R="1"/><Ticket N="116" T="01.11.2010 6:55:00" S="88.5" U="88.5" R="1"/></TicketType></ToStation><ToStation E="2005001" D="49"><TicketType ID="1"><Ticket N="8" T="31.10.2010 19:45:00" S="73.5"/><Ticket N="10" T="31.10.2010 20:03:00" S="73.5"/><Ticket N="14" T="31.10.2010 20:16:00" S="73.5"/><Ticket N="15" T="31.10.2010 20:17:00" S="73.5"/><Ticket N="16" T="31.10.2010 20:18:00" S="73.5"/><Ticket N="17" T="31.10.2010 20:18:00" S="73.5"/><Ticket N="24" T="31.10.2010 21:38:00" S="73.5"/><Ticket N="25" T="31.10.2010 21:39:00" S="73.5"/><Ticket N="27" T="31.10.2010 21:44:00" S="73.5"/><Ticket N="33" T="01.11.2010 4:50:00" S="73.5"/><Ticket N="47" T="01.11.2010 5:43:00" S="73.5"/><Ticket N="48" T="01.11.2010 5:46:00" S="73.5"/><Ticket N="51" T="01.11.2010 5:54:00" S="73.5"/><Ticket N="52" T="01.11.2010 5:55:00" S="147" R="1"/><Ticket N="54" T="01.11.2010 5:57:00" S="73.5"/><Ticket N="60" T="01.11.2010 5:59:00" S="147" R="1"/><Ticket N="61" T="01.11.2010 5:59:00" S="147" R="1"/><Ticket N="63" T="01.11.2010 6:00:00" S="73.5"/><Ticket N="64" T="01.11.2010 6:01:00" S="147" R="1"/><Ticket N="65" T="01.11.2010 6:02:00" S="147" R="1"/><Ticket N="67" T="01.11.2010 6:06:00" S="73.5"/><Ticket N="68" T="01.11.2010 6:08:00" S="147" R="1"/><Ticket N="69" T="01.11.2010 6:09:00" S="147" R="1"/><Ticket N="70" T="01.11.2010 6:16:00" S="73.5"/><Ticket N="73" T="01.11.2010 6:26:00" S="73.5"/><Ticket N="74" T="01.11.2010 6:26:00" S="73.5"/><Ticket N="76" T="01.11.2010 6:29:00" S="147" R="1"/><Ticket N="78" T="01.11.2010 6:30:00" S="147" R="1"/><Ticket N="80" T="01.11.2010 6:31:00" S="147" R="1"/><Ticket N="87" T="01.11.2010 6:36:00" S="73.5"/><Ticket N="88" T="01.11.2010 6:36:00" S="73.5"/><Ticket N="91" T="01.11.2010 6:37:00" S="73.5"/><Ticket N="94" T="01.11.2010 6:38:00" S="147" R="1"/><Ticket N="96" T="01.11.2010 6:38:00" S="73.5"/><Ticket N="97" T="01.11.2010 6:39:00" S="147" R="1"/><Ticket N="101" T="01.11.2010 6:40:00" S="147" R="1"/><Ticket N="102" T="01.11.2010 6:40:00" S="147" R="1"/><Ticket N="105" T="01.11.2010 6:41:00" S="73.5"/><Ticket N="119" T="01.11.2010 6:58:00" S="73.5"/><Ticket N="120" T="01.11.2010 6:58:00" S="73.5"/></TicketType><TicketType ID="1" L="2422"><Ticket N="11" T="31.10.2010 20:04:00" S="0" U="73.5" V="4" D="01880200120" F="ÅÐØÎÂ=ÞÍ"/><Ticket N="18" T="31.10.2010 20:33:00" S="0" U="73.5" V="4" D="02489300250" F="ÀÇÎÂÖÅÂ=ÊÑ"/><Ticket N="19" T="31.10.2010 20:34:00" S="0" U="73.5" V="4" D="02121838804" F="ÀÇÎÂÖÅÂÀ=Âß"/><Ticket N="21" T="31.10.2010 21:01:00" S="0" U="73.5" V="4" D="03013594100" F="ËÓÊÜßÍÎÂÀ=ÀÊ"/><Ticket N="50" T="01.11.2010 5:53:00" S="0" U="147" R="1" V="4" D="00602088496" F="ÈÂÀÍÎÂÀ=ÃÈ"/></TicketType><TicketType ID="1" L="2605"><Ticket N="23" T="31.10.2010 21:38:00" S="36.8" U="36.7"/><Ticket N="57" T="01.11.2010 5:58:00" S="73.5" U="73.5" R="1"/><Ticket N="84" T="01.11.2010 6:35:00" S="73.5" U="73.5" R="1"/><Ticket N="115" T="01.11.2010 6:54:00" S="73.5" U="73.5" R="1"/></TicketType><TicketType ID="1" L="2419"><Ticket N="75" T="01.11.2010 6:28:00" S="0" U="73.5" V="4" D="00755994781" F="ÒÐÓÁÊÈÍÀ=ËÏ"/></TicketType><TicketType ID="101"><Ticket N="117" T="01.11.2010 6:56:00" S="3443" C="00000000000001704655" K="1872358014"/></TicketType></ToStation><ToStation E="2004182" D="36"><TicketType ID="1"><Ticket N="26" T="31.10.2010 21:41:00" S="54"/><Ticket N="28" T="31.10.2010 21:45:00" S="108" P="01.11.2010" R="1"/><Ticket N="29" T="31.10.2010 23:28:00" S="54" P="01.11.2010"/><Ticket N="41" T="01.11.2010 5:39:00" S="108" R="1"/><Ticket N="59" T="01.11.2010 5:59:00" S="108" R="1"/><Ticket N="82" T="01.11.2010 6:32:00" S="108" R="1"/><Ticket N="108" T="01.11.2010 6:44:00" S="54"/></TicketType><TicketType ID="411"><Ticket N="83" T="01.11.2010 6:34:00" S="1508" C="00000000000001699370" K="2263159685"/></TicketType><TicketType ID="1" L="2422"><Ticket N="89" T="01.11.2010 6:36:00" S="0" U="108" R="1" V="4" D="00377277141" F="ÁÅÑÏÀËÎÂÀ=ÀÈ"/><Ticket N="99" T="01.11.2010 6:39:00" S="0" U="108" R="1" V="4" D="08257509989" F="ÇÅÍÈÍÀ=ÈÀ"/></TicketType><TicketType ID="108"><Ticket N="106" T="01.11.2010 6:42:00" S="508" C="00000000000001552969" K="2143846485"/></TicketType></ToStation><ToStation E="2004181" D="33"><TicketType ID="1" L="2422"><Ticket N="38" T="01.11.2010 5:33:00" S="0" U="99" R="1" V="4" D="01226403490" F="ØÓÑÒÎÂÀ=ÒÊ"/><Ticket N="44" T="01.11.2010 5:42:00" S="0" U="99" R="1" V="4" D="08641985609" F="ÆÓÊÎÂÀ=ÅÁ"/></TicketType><TicketType ID="1"><Ticket N="46" T="01.11.2010 5:43:00" S="99" R="1"/><Ticket N="49" T="01.11.2010 5:47:00" S="49.5"/><Ticket N="71" T="01.11.2010 6:17:00" S="49.5"/><Ticket N="81" T="01.11.2010 6:31:00" S="99" R="1"/><Ticket N="95" T="01.11.2010 6:38:00" S="49.5"/><Ticket N="103" T="01.11.2010 6:41:00" S="99" R="1"/><Ticket N="109" T="01.11.2010 6:44:00" S="49.5"/></TicketType></ToStation><ToStation E="2005315" D="56"><TicketType ID="1"><Ticket N="56" T="01.11.2010 5:58:00" S="168" R="1"/></TicketType></ToStation><ToStation E="2005166" D="46"><TicketType ID="1"><Ticket N="58" T="01.11.2010 5:59:00" S="69"/></TicketType></ToStation><ToStation E="2005046" D="26"><TicketType ID="1"><Ticket N="79" T="01.11.2010 6:31:00" S="39"/><Ticket N="114" T="01.11.2010 6:54:00" S="39"/><Ticket N="121" T="01.11.2010 6:59:00" S="39"/></TicketType></ToStation><ToStation E="2004923" D="38"><TicketType ID="1"><Ticket N="86" T="01.11.2010 6:36:00" S="114" R="1"/></TicketType></ToStation></FromStation></TPlan></TrainCat></Perevoz></KFile>
