<?xml version="1.0" encoding="windows-1251" standalone="no"?>
<KFile Name="K_B_00007117_000190_101111.XML" Version="1.0" Schema="2.0" Hash="99" CRC="301DCB8CF28B20F2"><Head NumTerm="7117" SmenaNum="190" TypeTerm="PKTK" INN="007839330845" PlaceTerm="2004003" Month="23" TimeOpen="11.11.2010 14:24:00" FirstTicket="452" Sum="1048.50" SumEKLZ="1048.50" Sup="228" TimeClose="11.11.2010 20:41:00" NumTickets="17" LenTape="1.89" Cancel="0" SumProc="1048.50" NumProc="16" SumServ="0" NDSServ="0" SCol="0" STax="0" CardIn="0" CardOut="0"/><History N="6"><Event N="1" T="11.11.2010 20:41:00" C="0" O="Output PKTK  001.023/05.12.06" E="0"/><Event N="2" T="14.11.2010 11:24:47" C="1" O="Create xx_pktk.dll v.1.0.0.10" E="0"/><Event N="3" T="14.11.2010 11:25:43" C="2" O="SPPD ARM2.exe v.1.3.0.26 tarif:t_001_04003_00038_100831.xml" E="0"/><Event N="4" T="22.11.2010 11:36:00" C="2" O="SPPD ARM2.exe v.1.3.0.26 tarif:t_001_04003_00038_100831.xml" E="0"/><Event N="5" T="22.11.2010 11:55:39" C="4" O="MTS+ Marsh75.exe ver. 10.6.9.100" E="0"/><Event N="6" T="22.11.2010 12:04:53" C="2" O="SPPD ARM2.exe v.1.3.0.28 tarif:t_001_04003_00038_100831.xml" E="0"/></History><ServOp><Test N="452" T="11.11.2010 14:24:00"/><Rep N="0" T="11.11.2010 20:41:00"/></ServOp><ZalogOp/><ServForms/><Perevoz Gkey="0600"><TrainCat Cat="Î"><TPlan ID="0"><FromStation E="2005001"><ToStation E="2004182"><TicketType ID="1"><Ticket N="453" T="11.11.2010 15:01:00" S="30"/><Ticket N="454" T="11.11.2010 15:01:00" S="30"/><Ticket N="455" T="11.11.2010 15:03:00" S="30"/><Ticket N="456" T="11.11.2010 15:03:00" S="30"/></TicketType></ToStation><ToStation E="2004181"><TicketType ID="1"><Ticket N="457" T="11.11.2010 15:06:00" S="30"/></TicketType></ToStation></FromStation><FromStation E="2004180"><ToStation E="2004178"><TicketType ID="1" L="2605"><Ticket N="458" T="11.11.2010 15:55:00" S="19.50" U="19.50"/></TicketType></ToStation><ToStation E="2004179"><TicketType ID="1" L="2605"><Ticket N="459" T="11.11.2010 15:55:00" S="15" U="15"/></TicketType></ToStation><ToStation E="2005001"><TicketType ID="1"><Ticket N="466" T="11.11.2010 19:44:00" S="73.50"/></TicketType></ToStation></FromStation><FromStation E="2004178"><ToStation E="2004177"><TicketType ID="1"><Ticket N="460" T="11.11.2010 16:21:00" S="30"/></TicketType></ToStation></FromStation><FromStation E="2004641"><ToStation E="2005001"><TicketType ID="1"><Ticket N="461" T="11.11.2010 18:17:00" S="178.50"/><Ticket N="463" T="11.11.2010 18:23:00" S="178.50"/></TicketType></ToStation><ToStation E="2004003"><TicketType ID="1" L="2422"><Ticket N="464" T="11.11.2010 18:26:00" S="0" U="193.50"/></TicketType></ToStation></FromStation><FromStation E="2005448"><ToStation E="2004182"><TicketType ID="1"><Ticket N="462" T="11.11.2010 18:21:00" S="153"/></TicketType></ToStation></FromStation><FromStation E="2004176"><ToStation E="2005001"><TicketType ID="1"><Ticket N="465" T="11.11.2010 18:54:00" S="150"/></TicketType></ToStation></FromStation><FromStation E="2005296"><ToStation E="2005001"><TicketType ID="1"><Ticket N="467" T="11.11.2010 19:45:00" S="70.50"/></TicketType></ToStation></FromStation><FromStation E="2004182"><ToStation E="2005001"><TicketType ID="1"><Ticket N="468" T="11.11.2010 20:21:00" S="30"/></TicketType></ToStation></FromStation></TPlan></TrainCat></Perevoz></KFile>
